calculadora/__init__.py
calculadora/calculos.py
calculadora/menu.py
calculadora_gustavo_felix-0.0.3.dist-info/METADATA
calculadora_gustavo_felix-0.0.3.dist-info/WHEEL
calculadora_gustavo_felix-0.0.3.dist-info/top_level.txt
calculadora_gustavo_felix-0.0.3.dist-info/RECORD
