Metadata-Version: 2.4
Name: calculadora-gustavo-felix
Version: 0.0.3
Summary: Uma simples calculadora.
Home-page: https://github.com/Gustavo-Felix/simple-package-template
Author: Gustavo Felix
Author-email: gustavofelix2007@gmail.com
Requires-Python: >=3.8
Dynamic: author
Dynamic: author-email
Dynamic: description
Dynamic: description-content-type
Dynamic: home-page
Dynamic: requires-python
Dynamic: summary
